llama_index/callbacks/opentelemetry/BUILD
llama_index/callbacks/opentelemetry/__init__.py
llama_index/callbacks/opentelemetry/base.py
llama_index_callbacks_opentelemetry-0.5.0.dist-info/METADATA
llama_index_callbacks_opentelemetry-0.5.0.dist-info/WHEEL
llama_index_callbacks_opentelemetry-0.5.0.dist-info/RECORD
